tessera/__init__.py
tessera/config.py
tessera/main.py
tessera/api/__init__.py
tessera/api/api_keys.py
tessera/api/assets.py
tessera/api/audit.py
tessera/api/audits.py
tessera/api/auth.py
tessera/api/bulk.py
tessera/api/contracts.py
tessera/api/dependencies.py
tessera/api/errors.py
tessera/api/impact.py
tessera/api/pagination.py
tessera/api/proposals.py
tessera/api/rate_limit.py
tessera/api/registrations.py
tessera/api/schemas.py
tessera/api/search.py
tessera/api/teams.py
tessera/api/types.py
tessera/api/users.py
tessera/api/webhooks.py
tessera/api/sync/__init__.py
tessera/api/sync/dbt.py
tessera/api/sync/graphql.py
tessera/api/sync/helpers.py
tessera/api/sync/openapi.py
tessera/cli/__init__.py
tessera/cli/dbt.py
tessera/connectors/__init__.py
tessera/connectors/bigquery.py
tessera/connectors/duckdb.py
tessera/db/__init__.py
tessera/db/database.py
tessera/db/models.py
tessera/models/__init__.py
tessera/models/acknowledgment.py
tessera/models/api_key.py
tessera/models/asset.py
tessera/models/bulk.py
tessera/models/contract.py
tessera/models/dependency.py
tessera/models/enums.py
tessera/models/proposal.py
tessera/models/registration.py
tessera/models/team.py
tessera/models/user.py
tessera/models/webhook.py
tessera/services/__init__.py
tessera/services/affected_parties.py
tessera/services/audit.py
tessera/services/auth.py
tessera/services/batch.py
tessera/services/cache.py
tessera/services/contract_publisher.py
tessera/services/expiration.py
tessera/services/graphql.py
tessera/services/metrics.py
tessera/services/openapi.py
tessera/services/schema_diff.py
tessera/services/schema_validator.py
tessera/services/slack.py
tessera/services/webhooks.py
tessera/services/avro/__init__.py
tessera/services/avro/converter.py
tessera/services/avro/validator.py
tessera/static/css/style.css
tessera/static/images/logo.png
tessera/static/js/api.js
tessera/templates/api_key_detail.html
tessera/templates/api_keys.html
tessera/templates/asset_detail.html
tessera/templates/assets.html
tessera_contracts-0.2.0.dist-info/METADATA
tessera_contracts-0.2.0.dist-info/WHEEL
tessera_contracts-0.2.0.dist-info/entry_points.txt
tessera_contracts-0.2.0.dist-info/licenses/LICENSE
tessera_contracts-0.2.0.dist-info/RECORD
