Metadata-Version: 2.4
Name: tessera-contracts
Version: 0.2.0
Summary: Data contract coordination for warehouses
Project-URL: Documentation, https://ashita-ai.github.io/tessera
Project-URL: Repository, https://github.com/ashita-ai/tessera
License-File: LICENSE
Requires-Python: >=3.11
Requires-Dist: alembic<2.0.0,>=1.14.0
Requires-Dist: argon2-cffi<24.0.0,>=23.0.0
Requires-Dist: asyncpg<1.0.0,>=0.30.0
Requires-Dist: email-validator<3.0.0,>=2.3.0
Requires-Dist: fastapi<1.0.0,>=0.115.0
Requires-Dist: greenlet<4.0.0,>=3.3.0
Requires-Dist: httpx<1.0.0,>=0.28.0
Requires-Dist: itsdangerous<3.0.0,>=2.0.0
Requires-Dist: jinja2<4.0.0,>=3.1.0
Requires-Dist: jsonschema<5.0.0,>=4.20.0
Requires-Dist: prometheus-client<1.0.0,>=0.21.0
Requires-Dist: pydantic-settings<3.0.0,>=2.6.0
Requires-Dist: pydantic<3.0.0,>=2.10.0
Requires-Dist: python-dotenv<2.0.0,>=1.0.0
Requires-Dist: python-multipart<1.0.0,>=0.0.12
Requires-Dist: pyyaml<7.0.0,>=6.0.0
Requires-Dist: redis<6.0.0,>=5.0.0
Requires-Dist: rich<14.0.0,>=13.0.0
Requires-Dist: slowapi<1.0.0,>=0.1.9
Requires-Dist: sqlalchemy<3.0.0,>=2.0.0
Requires-Dist: typer<1.0.0,>=0.15.0
Requires-Dist: uvicorn<1.0.0,>=0.32.0
Provides-Extra: avro
Requires-Dist: fastavro<2.0.0,>=1.8.0; extra == 'avro'
Provides-Extra: bigquery
Requires-Dist: google-cloud-bigquery<4.0.0,>=3.25.0; extra == 'bigquery'
Provides-Extra: demo
Requires-Dist: dbt-duckdb>=1.10.0; extra == 'demo'
Provides-Extra: dev
Requires-Dist: mypy<2.0.0,>=1.13.0; extra == 'dev'
Requires-Dist: pytest-asyncio<1.0.0,>=0.24.0; extra == 'dev'
Requires-Dist: pytest-cov<7.0.0,>=6.0.0; extra == 'dev'
Requires-Dist: pytest<9.0.0,>=8.0.0; extra == 'dev'
Requires-Dist: ruff<1.0.0,>=0.8.0; extra == 'dev'
Provides-Extra: docs
Requires-Dist: mkdocs-gen-files<1.0.0,>=0.5.0; extra == 'docs'
Requires-Dist: mkdocs-literate-nav<1.0.0,>=0.6.0; extra == 'docs'
Requires-Dist: mkdocs-material<10.0.0,>=9.5.0; extra == 'docs'
Requires-Dist: mkdocs<2.0.0,>=1.6.0; extra == 'docs'
Requires-Dist: mkdocstrings[python]<1.0.0,>=0.27.0; extra == 'docs'
Provides-Extra: duckdb
Requires-Dist: duckdb<2.0.0,>=1.0.0; extra == 'duckdb'
